derby/__init__.py
derby/__main__.py
derby/dice.py
derby/expr.py
derby/grammar.py
derby/parser.py
derby-0.7.2.dist-info/LICENSE
derby-0.7.2.dist-info/METADATA
derby-0.7.2.dist-info/WHEEL
derby-0.7.2.dist-info/top_level.txt
derby-0.7.2.dist-info/RECORD
