Metadata-Version: 2.1
Name: derby
Version: 0.7.2
Summary: A simple dice rolling library
Home-page: https://gitlab.com/micaiahparker/derby
Author: Micaiah Parker
Author-email: me@micaiahparker.com
License: MIT
Project-URL: Source, https://gitlab.com/micaiahparker/derby
Keywords: dice rolling games
Platform: UNKNOWN
Classifier: Development Status :: 3 - Alpha
Classifier: Intended Audience :: Developers
Classifier: License :: OSI Approved :: MIT License
Classifier: Programming Language :: Python :: 3.6
Requires-Python: >=3.6
Requires-Dist: lark-parser
